license_manager/command.py
license_manager/license.py
license_manager/main.py
license_manager/utils.py
license_manager-0.2.3.dist-info/entry_points.txt
license_manager-0.2.3.dist-info/WHEEL
license_manager-0.2.3.dist-info/METADATA
license_manager-0.2.3.dist-info/RECORD
