Metadata-Version: 2.1
Name: license-manager
Version: 0.2.3
Summary: 
Author: leaf
Author-email: ncoder@126.com
Requires-Python: >=3.6,<4.0
Classifier: Programming Language :: Python :: 3
Classifier: Programming Language :: Python :: 3.10
Classifier: Programming Language :: Python :: 3.6
Classifier: Programming Language :: Python :: 3.7
Classifier: Programming Language :: Python :: 3.8
Classifier: Programming Language :: Python :: 3.9
Requires-Dist: fire (>=0.4.0,<0.5.0)
Requires-Dist: pycryptodome (>=3.15.0,<4.0.0)
